test_pppppp/__init__.py
test_pppppp/core.py
test_pppppp/log.py
test_pppppp/server.py
test_pppppp/utils.py
test_pppppp-0.1.1.dist-info/METADATA
test_pppppp-0.1.1.dist-info/WHEEL
test_pppppp-0.1.1.dist-info/top_level.txt
test_pppppp-0.1.1.dist-info/RECORD
