Metadata-Version: 2.4
Name: test-pppppp
Version: 0.1.1
Summary: Add your description here
Requires-Python: >=3.13
Requires-Dist: anyio>=4.11.0
Requires-Dist: fastapi>=0.118.0
Requires-Dist: pytest>=8.4.2
Requires-Dist: pytest-asyncio>=1.2.0
Requires-Dist: pytest-tornasync>=0.6.0.post2
Requires-Dist: toml>=0.10.2
Requires-Dist: utils-tool==0.1.3
Requires-Dist: uvicorn>=0.37.0
